avro_codec/__init__.py
avro_codec-2.0.0.dist-info/DESCRIPTION.rst
avro_codec-2.0.0.dist-info/METADATA
avro_codec-2.0.0.dist-info/RECORD
avro_codec-2.0.0.dist-info/WHEEL
avro_codec-2.0.0.dist-info/metadata.json
avro_codec-2.0.0.dist-info/top_level.txt
