Metadata-Version: 2.0
Name: avro-codec
Version: 2.0.0
Summary: An avro codec which exposes an API similar to the standard library's marshal, pickle and json modules
Home-page: http://github.com/gamechanger/avro_codec
Author: Data and Analytics
Author-email: data@gc.com
License: MIT
Keywords: avro encode decode codec
Platform: UNKNOWN
Requires-Dist: avro (==1.7.7)
Requires-Dist: fastavro (==0.22.5)
